GA 3.4/mux.v
// output = A (when control == 00) or B (when control == 01) or
//          C (when control == 10) or D (when control == 11)
module mux4(out, A, B, C, D, control); // a 4-input multiplexer
   output      out;
   input       A, B, C, D;
   input [1:0] control;  // multiple bit signal (2-bits)
   // use control[0] and  control[1] as inputs to multiplexers
   wire multi_ab, multi_cd;

   // control[0] = 0 for A and B
   mux2 m_ab(multi_ab, A, B, control[0]);
   // control[0] = 1 for C and D
   mux2 m_cd(multi_cd, C, D, control[0]);

   // control[1] for both?
   mux2 m_all(out, multi_ab, multi_cd, control[1]);

endmodule // mux4

// Here is an implementation of a 2-to-1 multiplexer for you to use
// output = A (when control == 0) or B (when control == 1)
module mux2(out, A, B, control);   // a 2-input multiplexer
   output      out;
   input       A, B;
   input       control;
   wire        wA, wB, not_control;
        
   not   n1(not_control, control);
   and   a1(wA, A, not_control);
   and   a2(wB, B, control);
   or    o1(out, wA, wB);
endmodule // mux2

GA 3.4/mux_tb.v
module test;

    // cycle through all combinations of A, B, C, D every 16 time units
    reg A = 0;
    reg B = 0;
    reg C = 0;
    reg D = 0;
     
    reg [1:0] control = 0;
     
    wire out;
    mux4 m4(out, A, B, C, D, control);

    initial begin
        $dumpfile("mux4.vcd");
        $dumpvars(0, test);

        //This is a non-exhaustive test suite, you should build a better one to test your lab
        A = 0; B = 1; C = 1; D = 1; control = 0; #10
        A = 1; B = 0; C = 0; D = 0; control = 0; #10
        A = 1; B = 0; C = 1; D = 1; control = 1; #10
        A = 0; B = 1; C = 0; D = 0; control = 1; #10
        A = 1; B = 1; C = 0; D = 1; control = 2; #10
        A = 0; B = 0; C = 1; D = 0; control = 2; #10
        A = 1; B = 1; C = 1; D = 0; control = 3; #10
        A = 0; B = 0; C = 0; D = 1; control = 3; #10
          
        $finish;        // end the simulation
    end

    initial begin
        $display("A B C D s o");
        $monitor("inputs = %b %b %b %b %d  outputs = %b", A, B, C, D, control, out);
    end

endmodule // mux4_test

GA 3.4/mux4.vcd
$date
	Tue Jan 28 16:10:53 2025
$end
$version
	Icarus Verilog
$end
$timescale
	1s
$end
$scope module test $end
$var wire 1 ! out $end
$var reg 1 " A $end
$var reg 1 # B $end
$var reg 1 $ C $end
$var reg 1 % D $end
$var reg 2 & control [1:0] $end
$scope module m4 $end
$var wire 1 " A $end
$var wire 1 # B $end
$var wire 1 $ C $end
$var wire 1 % D $end
$var wire 2 ' control [1:0] $end
$var wire 1 ! out $end
$var wire 1 ( multi_cd $end
$var wire 1 ) multi_ab $end
$scope module m_ab $end
$var wire 1 " A $end
$var wire 1 # B $end
$var wire 1 * control $end
$var wire 1 + not_control $end
$var wire 1 ) out $end
$var wire 1 , wA $end
$var wire 1 - wB $end
$upscope $end
$scope module m_all $end
$var wire 1 ) A $end
$var wire 1 . control $end
$var wire 1 / not_control $end
$var wire 1 ! out $end
$var wire 1 0 wA $end
$var wire 1 1 wB $end
$var wire 1 ( B $end
$upscope $end
$scope module m_cd $end
$var wire 1 $ A $end
$var wire 1 % B $end
$var wire 1 2 control $end
$var wire 1 3 not_control $end
$var wire 1 ( out $end
$var wire 1 4 wA $end
$var wire 1 5 wB $end
$upscope $end
$upscope $end
$upscope $end
$enddefinitions $end
#0
$dumpvars
05
14
13
02
01
00
1/
0.
0-
0,
1+
0*
0)
1(
b0 '
b0 &
1%
1$
1#
0"
0!
$end
#10
1!
10
0(
1)
04
1,
0%
0$
0#
1"
#20
0!
00
0)
0,
0+
03
15
1(
1*
12
04
b1 &
b1 '
1%
1$
#30
1!
10
0(
1)
05
1-
0%
0$
1#
0"
#40
0!
1,
1)
00
1+
0-
13
0/
01
0(
0*
02
1.
05
b10 &
b10 '
1%
1"
#50
1!
11
1(
0)
14
0,
0%
1$
0#
0"
#60
0!
01
0(
04
0+
1-
03
1)
1*
12
0,
b11 &
b11 '
1#
1"
#70
1!
11
1(
0)
15
0-
1%
0$
0#
0"
