Lab 1.2.1/comparator1.v
module comparator1(pout, qout, a, b, pin, qin);
 output pout, qout;
 input  a, b, pin, qin;


 // wire declarations
 wire   not_p, not_q, not_a, not_b;
 wire   po2, po4, po8, po9, po10, po12, po13, po14, po15;
 wire   qo1, qo4, qo5, qo6, qo7, qo12, qo14, qo15, qo16;


 // input complements
 not  np(not_p, pin);
 not  nq(not_q, qin);
 not  na(not_a, a);
 not  nb(not_b, b);


 // po
 and  p2(po2, not_p, not_q, a, not_b);
 and  p4(po4, pin, not_q, not_a, not_b);
 and  p8(po8, pin, not_q, not_a, b);
 and  p9(po9, pin, not_q, a, not_b);
 and  p10(po10, pin, not_q, a, b);
 and  p12(po12, pin, qin, not_a, not_b);
 and  p13(po13, pin, qin, not_a, b);
 and  p14(po14, pin, qin, a, not_b);
 and  p15(po15, pin, qin, a, b);
 or   op(pout, po2, po4, po8, po9, po10, po12, po13, po14, po15);


 // qo
 and  q1(qo1, not_p, not_q, not_a, b);
 and  q4(qo4, not_p, qin, not_a, not_b);
 and  q5(qo5, not_p, qin, not_a, b);
 and  q6(qo6, not_p, qin, a, not_b);
 and  q7(qo7, not_p, qin, a, b);
 and  q12(qo12, pin, qin, not_a, not_b);
 and  q14(qo14, pin, qin, not_a, b);
 and  q15(qo15, pin, qin, a, not_b);
 and  q16(qo16, pin, qin,a, b);
 or   oq(qout, qo1, qo4, qo5, qo6, qo7, qo12, qo14, qo15,qo16);


endmodule // comparator

Lab 1.2.1/comparator1_tb.v
module comparator1_test;

   reg pin = 0;
   reg qin = 0;
   reg a = 0;
   reg b = 0;
   
   initial begin
     $dumpfile("commparator1_test.vcd");
     $dumpvars(0, comparator1_test);
    
     #1 pin = 0; qin = 0; a = 0; b = 0;
     #1 pin = 0; qin = 0; a = 0; b = 1;
     #1 pin = 0; qin = 0; a = 1; b = 0;
     #1 pin = 0; qin = 0; a = 1; b = 1;

     #1 pin = 0; qin = 1; a = 0; b = 0;
     #1 pin = 0; qin = 1; a = 0; b = 1;
     #1 pin = 0; qin = 1; a = 1; b = 0;
     #1 pin = 0; qin = 1; a = 1; b = 1;

     #1 pin = 1; qin = 0; a = 0; b = 0;
     #1 pin = 1; qin = 0; a = 0; b = 1;
     #1 pin = 1; qin = 0; a = 1; b = 0;
     #1 pin = 1; qin = 0; a = 1; b = 1;

     #1 pin = 1; qin = 1; a = 0; b = 0;
     #1 pin = 1; qin = 1; a = 0; b = 1;
     #1 pin = 1; qin = 1; a = 1; b = 0;
     #1 pin = 1; qin = 1; a = 1; b = 1;

     $finish;
   end

   wire pout, qout;
   comparator1 c1(pout, qout, a, b, pin, qin);    

   initial
       $monitor("pin,qin = %b%b ab = %b%b pout,qout = %b%b", pin, qin, a, b, pout, qout);
 
   
endmodule // alu1_test

Lab 1.2.1/commparator1_test.vcd
$date
	Sun Jan 26 17:09:43 2025
$end
$version
	Icarus Verilog
$end
$timescale
	1s
$end
$scope module comparator1_test $end
$var wire 1 ! qout $end
$var wire 1 " pout $end
$var reg 1 # a $end
$var reg 1 $ b $end
$var reg 1 % pin $end
$var reg 1 & qin $end
$scope module c1 $end
$var wire 1 # a $end
$var wire 1 $ b $end
$var wire 1 ' not_a $end
$var wire 1 ( not_b $end
$var wire 1 ) not_p $end
$var wire 1 * not_q $end
$var wire 1 % pin $end
$var wire 1 + po10 $end
$var wire 1 , po12 $end
$var wire 1 - po13 $end
$var wire 1 . po14 $end
$var wire 1 / po15 $end
$var wire 1 0 po2 $end
$var wire 1 1 po4 $end
$var wire 1 2 po8 $end
$var wire 1 3 po9 $end
$var wire 1 " pout $end
$var wire 1 & qin $end
$var wire 1 4 qo1 $end
$var wire 1 5 qo12 $end
$var wire 1 6 qo14 $end
$var wire 1 7 qo15 $end
$var wire 1 8 qo16 $end
$var wire 1 9 qo4 $end
$var wire 1 : qo5 $end
$var wire 1 ; qo6 $end
$var wire 1 < qo7 $end
$var wire 1 ! qout $end
$upscope $end
$upscope $end
$enddefinitions $end
#0
$dumpvars
0<
0;
0:
09
08
07
06
05
04
03
02
01
00
0/
0.
0-
0,
0+
1*
1)
1(
1'
0&
0%
0$
0#
0"
0!
$end
#2
1!
0(
14
1$
#3
1"
0!
10
1(
04
0'
0$
1#
#4
0"
00
0(
1$
#5
1!
19
1(
1'
0*
0$
0#
1&
#6
09
0(
1:
1$
#7
1!
1;
1(
0:
0'
0$
1#
#8
0;
0(
1<
1$
#9
1"
0!
11
1(
1'
1*
0<
0)
0$
0#
0&
1%
#10
01
0(
12
1$
#11
1"
13
1(
02
0'
0$
1#
#12
03
0(
1+
1$
#13
1!
1"
1,
15
1(
1'
0+
0*
0$
0#
1&
#14
0,
05
0(
1-
16
1$
#15
1"
1!
1.
17
1(
0-
06
0'
0$
1#
#16
0.
07
0(
1/
18
1$
