GA 1.8/blackbox.v
module blackbox(z, x, b, d);
    output z;
    input  x, b, d;
    wire   w02, w13, w16, w18, w31, w33, w34, w37, w39, w49, w55, w62, w69, w82, w84, w91, w95, w97, w99;
    and a59(z, w34, w39);
    or  o25(w34, w49, w18);
    not n57(w18, w49);
    or  o98(w39, w69, w99);
    and a6(w99, w55, w91);
    not n28(w55, w91);
    or  o66(w49, w16, w62);
    and a11(w16, w02, w84);
    not n5(w02, b);
    not n48(w84, d);
    and a14(w62, b, w37, d);
    not n42(w37, x);
    and a78(w91, b, w13);
    or  o21(w13, x, w33);
    and a46(w33, d, w82);
    not n12(w82, x);
    and a87(w69, w97, w95);
    not n96(w97, b);
    or  o15(w95, x, w31);
    not n1(w31, d);
endmodule // blackbox

GA 1.8/blackbox_tb.v
module blackbox_test;
    reg a,b,c;
    wire z;
    blackbox ex1(z, a, b, c);
    initial begin               // initial = run at beginning of simulation
                // begin/end = associate block with initial

        $dumpfile("ex.vcd");    // name of dump file to create (used for waveform viewer)
        $dumpvars(0,blackbox_test);   // record all signals of module "ex_test" and sub-modules
        a = 0; b = 0; c = 0; # 10;     // set initial values and wait 10 time units
        a = 1; b = 0; c = 0; # 10; 
        a = 1; b = 1; c = 0; # 10;
        a = 0; b = 1; c = 0; # 10; 
        a = 0; b = 1; c = 1; # 10;
        a = 1; b = 0; c = 1; # 10;
        a = 0; b = 0; c = 1; # 10; 
        a = 1; b = 1; c = 1; # 10; 

        $finish;                // end the simulation
    end                 

    initial
        $monitor("At time %2t, a = %d b = %d c = %d z = %d",
                $time, a,b,c,z);

endmodule // blackbox_test

GA 1.8/ex.vcd
$date
	Tue Jan 21 16:32:13 2025
$end
$version
	Icarus Verilog
$end
$timescale
	1s
$end
$scope module blackbox_test $end
$var wire 1 ! z $end
$var reg 1 " a $end
$var reg 1 # b $end
$var reg 1 $ c $end
$scope module ex1 $end
$var wire 1 # b $end
$var wire 1 $ d $end
$var wire 1 % w02 $end
$var wire 1 & w13 $end
$var wire 1 ' w16 $end
$var wire 1 ( w18 $end
$var wire 1 ) w31 $end
$var wire 1 * w33 $end
$var wire 1 + w34 $end
$var wire 1 , w37 $end
$var wire 1 - w39 $end
$var wire 1 . w49 $end
$var wire 1 / w55 $end
$var wire 1 0 w62 $end
$var wire 1 1 w69 $end
$var wire 1 2 w82 $end
$var wire 1 3 w84 $end
$var wire 1 4 w91 $end
$var wire 1 5 w95 $end
$var wire 1 6 w97 $end
$var wire 1 7 w99 $end
$var wire 1 " x $end
$var wire 1 ! z $end
$upscope $end
$upscope $end
$enddefinitions $end
#0
$dumpvars
07
16
15
04
13
12
11
00
1/
1.
1-
1,
1+
0*
1)
0(
1'
0&
1%
0$
0#
0"
1!
$end
#10
0,
1&
02
1"
#20
0!
1(
1+
0-
0.
0'
0/
07
01
0%
14
06
1#
#30
1/
04
1,
0&
12
0"
#40
0!
0-
0/
07
0(
14
1.
1&
05
03
10
1*
0)
1$
#50
1!
1(
1+
1-
0.
1/
0*
11
1%
00
04
16
0,
02
15
0#
1"
#60
0!
0-
1*
01
1,
1&
12
05
0"
#70
0!
0-
0/
07
0*
0%
14
06
0,
02
15
1#
1"
