GA 1.7/blackbox.v
module blackbox(z, m, s, h);
    output z;
    input  m, s, h;
    wire   w15, w17, w35, w36, w38, w51, w53, w54, w57, w59, w63, w65, w67, w69, w71, w80, w83, w84, w87, w92;
    or  o11(z, w59, w53, w38);
    and a12(w59, w67, w36, w71);
    not n97(w71, w35);
    and a19(w53, w36, w35, w67);
    and a28(w38, w92, w15);
    not n66(w92, w36);
    or  o98(w15, w57, w80);
    and a58(w57, w67, w35);
    and a55(w80, w69, w67);
    not n95(w69, w35);
    and a39(w36, m, w84);
    or  o40(w84, w65, w63);
    not n77(w65, s);
    and a2(w63, h, s);
    or  o14(w35, h, w51, s);
    not n96(w51, m);
    and a27(w67, m, w17);
    or  o0(w17, s, w87);
    and a26(w87, w83, w54);
    not n79(w83, h);
    not n32(w54, s);
endmodule // blackbox

GA 1.7/blackbox_tb.v
module blackbox_test;
    reg a,b,c;
    wire z;
    blackbox ex1(z, a, b, c);
    initial begin               // initial = run at beginning of simulation
                // begin/end = associate block with initial

        $dumpfile("ex.vcd");    // name of dump file to create (used for waveform viewer)
        $dumpvars(0,blackbox_test);   // record all signals of module "ex_test" and sub-modules
        a = 0; b = 0; c = 0; # 10;     // set initial values and wait 10 time units
        a = 1; b = 0; c = 0; # 10; 
        a = 1; b = 1; c = 0; # 10;
        a = 0; b = 1; c = 0; # 10; 
        a = 0; b = 1; c = 1; # 10;
        a = 1; b = 0; c = 1; # 10;
        a = 0; b = 0; c = 1; # 10; 
        a = 1; b = 1; c = 1; # 10; 

        $finish;                // end the simulation
    end                 

    initial
        $monitor("At time %2t, a = %d b = %d c = %d z = %d",
                 $time, a,b,c,z);

endmodule // blackbox_test

GA 1.7/ex.vcd
$date
	Tue Jan 21 16:28:14 2025
$end
$version
	Icarus Verilog
$end
$timescale
	1s
$end
$scope module blackbox_test $end
$var wire 1 ! z $end
$var reg 1 " a $end
$var reg 1 # b $end
$var reg 1 $ c $end
$scope module ex1 $end
$var wire 1 $ h $end
$var wire 1 " m $end
$var wire 1 # s $end
$var wire 1 % w15 $end
$var wire 1 & w17 $end
$var wire 1 ' w35 $end
$var wire 1 ( w36 $end
$var wire 1 ) w38 $end
$var wire 1 * w51 $end
$var wire 1 + w53 $end
$var wire 1 , w54 $end
$var wire 1 - w57 $end
$var wire 1 . w59 $end
$var wire 1 / w63 $end
$var wire 1 0 w65 $end
$var wire 1 1 w67 $end
$var wire 1 2 w69 $end
$var wire 1 3 w71 $end
$var wire 1 4 w80 $end
$var wire 1 5 w83 $end
$var wire 1 6 w84 $end
$var wire 1 7 w87 $end
$var wire 1 8 w92 $end
$var wire 1 ! z $end
$upscope $end
$upscope $end
$enddefinitions $end
#0
$dumpvars
18
17
16
15
04
03
02
01
10
0/
0.
0-
1,
0+
1*
0)
0(
1'
1&
0%
0$
0#
0"
0!
$end
#10
14
1.
12
13
1%
1!
08
0'
0-
0+
1(
0*
11
1"
#20
1)
1!
18
0(
04
0.
06
02
1-
0+
03
07
00
1'
0,
1#
#30
0!
0)
0%
0-
1*
01
0"
#40
16
1/
05
1$
#50
0%
0!
08
0-
0+
10
0/
0&
1,
1(
0*
01
0#
1"
#60
18
0(
1*
0"
#70
1%
1!
1-
1+
11
08
00
1/
1&
0,
1(
0*
1#
1"
